LICENCE.txt
MANIFEST.in
README.rst
setup.py
Optimus_foundation_5.egg-info/PKG-INFO
Optimus_foundation_5.egg-info/SOURCES.txt
Optimus_foundation_5.egg-info/dependency_links.txt
Optimus_foundation_5.egg-info/not-zip-safe
Optimus_foundation_5.egg-info/requires.txt
Optimus_foundation_5.egg-info/top_level.txt
optimus_foundation_5/README.rst
optimus_foundation_5/__init__.py
optimus_foundation_5/gemsets.txt
optimus_foundation_5/scripts/__init__.py.tpl
optimus_foundation_5/scripts/babel.cfg.tpl
optimus_foundation_5/scripts/config.rb.tpl
optimus_foundation_5/scripts/gitignore.tpl
optimus_foundation_5/scripts/pages.py.tpl
optimus_foundation_5/scripts/prod_settings.py.tpl
optimus_foundation_5/scripts/settings.py.tpl
optimus_foundation_5/sources/css/app.css
optimus_foundation_5/sources/foundation5/foundation.scss
optimus_foundation_5/sources/foundation5/normalize.scss
optimus_foundation_5/sources/foundation5/foundation/_functions.scss
optimus_foundation_5/sources/foundation5/foundation/_settings.scss
optimus_foundation_5/sources/foundation5/foundation/components/_accordion.scss
optimus_foundation_5/sources/foundation5/foundation/components/_alert-boxes.scss
optimus_foundation_5/sources/foundation5/foundation/components/_block-grid.scss
optimus_foundation_5/sources/foundation5/foundation/components/_breadcrumbs.scss
optimus_foundation_5/sources/foundation5/foundation/components/_button-groups.scss
optimus_foundation_5/sources/foundation5/foundation/components/_buttons.scss
optimus_foundation_5/sources/foundation5/foundation/components/_clearing.scss
optimus_foundation_5/sources/foundation5/foundation/components/_dropdown-buttons.scss
optimus_foundation_5/sources/foundation5/foundation/components/_dropdown.scss
optimus_foundation_5/sources/foundation5/foundation/components/_flex-video.scss
optimus_foundation_5/sources/foundation5/foundation/components/_forms.scss
optimus_foundation_5/sources/foundation5/foundation/components/_global.scss
optimus_foundation_5/sources/foundation5/foundation/components/_grid.scss
optimus_foundation_5/sources/foundation5/foundation/components/_inline-lists.scss
optimus_foundation_5/sources/foundation5/foundation/components/_joyride.scss
