Metadata-Version: 1.1
Name: Optimus-foundation-5
Version: 5.2.2.1
Summary: 
